src/__init__.py
src/__main__.py
src/color_utils.py
src/settings.py
osx_colors-1.1.0.dist-info/LICENSE
osx_colors-1.1.0.dist-info/METADATA
osx_colors-1.1.0.dist-info/WHEEL
osx_colors-1.1.0.dist-info/entry_points.txt
osx_colors-1.1.0.dist-info/top_level.txt
osx_colors-1.1.0.dist-info/RECORD
