Metadata-Version: 2.1
Name: osx-colors
Version: 1.1.0
Summary: Set osxs accent/highlight colors using the commandline
Home-page: https://github.com/yuhonas/osx-colors
Author: Clint Plummer
Author-email: hello@clintp.xyz
License: MIT
Keywords: osx colorscheme terminal-emulators changing-colorschemes
Platform: Darwin
Classifier: Environment :: MacOS X
Classifier: Operating System :: MacOS
Classifier: Programming Language :: Python :: 3.8
Classifier: Programming Language :: Python :: 3.9
Classifier: Programming Language :: Python :: 3.10
Classifier: Programming Language :: Python :: 3.11
Requires-Python: <4,>=3.8
License-File: LICENSE
